dalmatian/__init__.py
dalmatian/core.py
dalmatian/schema.py
dalmatian/wmanager.py
firecloud_dalmatian-0.0.20.dist-info/METADATA
firecloud_dalmatian-0.0.20.dist-info/WHEEL
firecloud_dalmatian-0.0.20.dist-info/top_level.txt
firecloud_dalmatian-0.0.20.dist-info/RECORD
