Metadata-Version: 2.2
Name: firecloud-dalmatian
Version: 0.0.20
Summary: Utilities for interacting with Terra via Pandas dataframes
Author-email: Francois Aguet <francois@broadinstitute.org>
Maintainer-email: Francois Aguet <francois@broadinstitute.org>
Project-URL: Repository, https://github.com/getzlab/dalmatian.git
Keywords: Workflow manager,Terra
Classifier: Development Status :: 4 - Beta
Classifier: Programming Language :: Python :: 3
Classifier: Intended Audience :: Science/Research
Classifier: Topic :: Scientific/Engineering :: Bio-Informatics
Classifier: Topic :: Scientific/Engineering :: Interface Engine/Protocol Translator
Requires-Dist: numpy
Requires-Dist: matplotlib
Requires-Dist: pandas
Requires-Dist: pytz
Requires-Dist: firecloud>=0.16.9
Requires-Dist: ipython
Requires-Dist: iso8601
Requires-Dist: google-cloud-storage>=1.13.2
Requires-Dist: agutil>=4.0.2
Requires-Dist: crayons>=0.2.0
Requires-Dist: hound>=0.2.0
